expert_score/__init__.py
expert_score/expert.py
expert_score/aspects/__init__.py
expert_score/aspects/extraction.py
expert_score/matching/__init__.py
expert_score/matching/match.py
expert_score/matching/utils.py
expert_score/utils/__init__.py
expert_score/utils/api_llm.py
expert_score/utils/json_parsing.py
expert_score-0.0.1.dist-info/LICENSE.txt
expert_score-0.0.1.dist-info/METADATA
expert_score-0.0.1.dist-info/WHEEL
expert_score-0.0.1.dist-info/top_level.txt
expert_score-0.0.1.dist-info/RECORD
