Metadata-Version: 2.2
Name: expert-score
Version: 0.0.1
Summary: The implementation of the ExPerT score.
Home-page: https://github.com/alirezasalemi7/ExPerT
Author: Alireza Salemi
Author-email: Alireza Salemi <asalemi@cs.umass.edu>
License: MIT License
Classifier: Programming Language :: Python :: 3
Classifier: License :: OSI Approved :: MIT License
Classifier: Operating System :: OS Independent
Requires-Python: >=3.8
License-File: LICENSE.txt
Requires-Dist: backoff==2.2.1
Requires-Dist: json5==0.9.25
Requires-Dist: openai==1.60.1
Requires-Dist: parse==1.20.2
Requires-Dist: protobuf==5.29.3
Requires-Dist: setuptools==75.2.0
Requires-Dist: tqdm==4.66.5
Requires-Dist: transformers==4.45.2
Requires-Dist: vllm==0.6.6
Requires-Dist: google-generativeai==0.8.4
Dynamic: author
Dynamic: home-page
